LICENSE.txt
README.md
setup.py
feature_engineering/__init__.py
feature_engineering/feature_engineering.py
feature_engineering.egg-info/PKG-INFO
feature_engineering.egg-info/SOURCES.txt
feature_engineering.egg-info/dependency_links.txt
feature_engineering.egg-info/requires.txt
feature_engineering.egg-info/top_level.txt