Metadata-Version: 2.1
Name: feature_engineering
Version: 2.1.4
Summary: Unleash the Power of Your Data with Feature Engineering: The Ultimate Python Library for Machine Learning Preprocessing and Enhancement
Home-page: https://github.com/knowusuboaky/feature_engineering
Author: Kwadwo Daddy Nyame Owusu - Boakye
Author-email: kwadwo.owusuboakye@outlook.com
Keywords: machine learning,data preprocessing,feature engineering,data transformation,data cleaning,outlier handling,imputation,scaling,one-hot encoding,feature selection,variance threshold,correlation filtering,embedded methods,wrapper methods,class imbalance,sampling techniques,hyperparameter tuning,model optimization,categorical data processing,numeric data processing,date feature extraction,custom transformers,Python,data science,predictive modeling,classification,regression,ML workflows,dat
Classifier: Development Status :: 3 - Alpha
Classifier: Intended Audience :: Developers
Classifier: Topic :: Software Development :: Build Tools
Classifier: License :: OSI Approved :: MIT License
Classifier: Programming Language :: Python :: 3
Classifier: Programming Language :: Python :: 3.6
Classifier: Programming Language :: Python :: 3.7
Classifier: Programming Language :: Python :: 3.8
Classifier: Programming Language :: Python :: 3.9
Classifier: Programming Language :: Python :: 3.10
Classifier: Programming Language :: Python :: 3.11
Classifier: Programming Language :: Python :: 3.12
Requires-Python: >=3.6
License-File: LICENSE.txt
Requires-Dist: pandas>=1.1.5
Requires-Dist: numpy>=1.19.5
Requires-Dist: scikit-learn>=0.24
Requires-Dist: imbalanced-learn>=0.7.0
Requires-Dist: holidays>=0.10.3
Requires-Dist: ipywidgets>=7.5.1
